{
  "version": "7",
  "dialect": "postgresql",
  "entries": [
    {
      "idx": 0,
      "version": "7",
      "when": 1783636059018,
      "tag": "0000_foamy_storm",
      "breakpoints": true
    },
    {
      "idx": 1,
      "version": "7",
      "when": 1783650827117,
      "tag": "0001_jazzy_mercury",
      "breakpoints": true
    },
    {
      "idx": 2,
      "version": "7",
      "when": 1783655896974,
      "tag": "0002_bored_zaladane",
      "breakpoints": true
    },
    {
      "idx": 3,
      "version": "7",
      "when": 1783914154572,
      "tag": "0003_fair_maelstrom",
      "breakpoints": true
    }
  ]
}